sheetiq/__init__.py
sheetiq/example.py
sheetiq/sheetiq.py
sheetiq/types.py
sheetiq-0.1.4.dist-info/licenses/LICENSE
sheetiq-0.1.4.dist-info/METADATA
sheetiq-0.1.4.dist-info/WHEEL
sheetiq-0.1.4.dist-info/top_level.txt
sheetiq-0.1.4.dist-info/RECORD
