Metadata-Version: 2.4
Name: sheetiq
Version: 0.1.4
Summary: Python SDK for accessing and updating Google Sheets via docapi.datafetchpro.com
Author-email: Ali Raza <you@example.com>
License: MIT
Project-URL: Homepage, https://docapi.datafetchpro.com
Project-URL: Repository, https://github.com/aliraza948/sheetiqp
Requires-Python: >=3.7
License-File: LICENSE
Requires-Dist: requests
Dynamic: license-file
